{
  "thermal_mass": 11,
  "conductivity": 0.45,
  "insulation_r": 7,
  "dissipation_rate": 0.07,
  "is_airtight": true,
  "porousness": 0.42,
  "adhesion": 0.6,
  "ousia_affinity": {
    "eterna": 0.08,
    "arcana": 0.15,
    "quanta": 0.4,
    "rectification": 0.07
  },
  "ousia_capacity": 10,
  "note": "Coarse dirt \u2014 gravelly, more porous and irregular than standard dirt",
  "block": "minecraft:coarse_dirt",
  "thickness_fraction": 1.0,
  "electrically_conductive": false,
  "thermal_crack_threshold": 800.0,
  "thermal_crack_rate": 0.001,
  "structural": {
    "compressive_strength_kpa": 80,
    "tensile_strength_kpa": 30,
    "shear_strength_kpa": 20,
    "fracture_toughness": 0.04,
    "density_kg_m3": 1150,
    "is_structural_frame": false,
    "load_transfer_range": 1,
    "failure_mode": "CRUMBLE",
    "failure_threshold_fraction": 1.0,
    "crack_threshold_fraction": 0.85,
    "fragment_min_size": 4,
    "fragment_initial_velocity_scale": 1.0,
    "cave_in_radius_override": -1,
    "shockwave_amplification": 1.2,
    "shockwave_absorption": 0.68
  }
}