{
  "thermal_mass": 12,
  "conductivity": 0.14,
  "insulation_r": 1.0,
  "dissipation_rate": 0.04,
  "is_airtight": true,
  "porousness": 0.2,
  "adhesion": 0.5,
  "ousia_affinity": {
    "eterna": 0.32,
    "arcana": 0.12,
    "quanta": 0.5,
    "rectification": 0.15
  },
  "ousia_capacity": 12,
  "note": "Bloodshroom log \u2014 blood slime island mushroom-wood, dark red biological material",
  "block": "tconstruct:bloodshroom_log",
  "thickness_fraction": 1.0,
  "electrically_conductive": false,
  "thermal_crack_threshold": 165.0,
  "thermal_crack_rate": 0.003,
  "structural": {
    "compressive_strength_kpa": 18000,
    "tensile_strength_kpa": 22000,
    "shear_strength_kpa": 6000,
    "fracture_toughness": 0.42,
    "density_kg_m3": 600,
    "is_structural_frame": false,
    "load_transfer_range": 1,
    "failure_mode": "CRUMBLE",
    "failure_threshold_fraction": 1.0,
    "crack_threshold_fraction": 0.65,
    "fragment_min_size": 4,
    "fragment_initial_velocity_scale": 1.0,
    "cave_in_radius_override": -1,
    "shockwave_amplification": 1.0,
    "shockwave_absorption": 0.3
  },
  "on_fire": {
    "temp": 285,
    "result": "minecraft:air",
    "requires_oxygen": true
  },
  "on_char": {
    "temp": 240,
    "result": "minecraft:air",
    "requires_oxygen": false
  }
}